[
  {
    "id": 1,
    "imagePath": "level_123.png",
    "answer": "sunburn",
    "hint": "Skin burned by sun"
  },
  {
    "id": 2,
    "imagePath": "level_152.png",
    "answer": "seahorse",
    "hint": "A small sea animal shaped like a horse"
  },
  {
    "id": 3,
    "imagePath": "level_107.png",
    "answer": "sunlight",
    "hint": "Light coming from the sun"
  },
  {
    "id": 4,
    "imagePath": "level_22.png",
    "answer": "brainstorm",
    "hint": "A brain making a storm"
  },
  {
    "id": 5,
    "imagePath": "level_75.png",
    "answer": "waterdrop",
    "hint": "A drop of water"
  },
  {
    "id": 6,
    "imagePath": "level_183.png",
    "answer": "motorbike",
    "hint": "Two wheeled motor vehicle"
  },
  {
    "id": 7,
    "imagePath": "level_48.png",
    "answer": "airplane",
    "hint": "A plane made from air"
  },
  {
    "id": 8,
    "imagePath": "level_158.png",
    "answer": "tablespoon",
    "hint": "A large spoon for serving"
  },
  {
    "id": 9,
    "imagePath": "level_118.png",
    "answer": "cloudnine",
    "hint": "Floating happily on clouds"
  },
  {
    "id": 10,
    "imagePath": "level_172.png",
    "answer": "overcoat",
    "hint": "A coat worn over clothes"
  },
  {
    "id": 11,
    "imagePath": "level_42.png",
    "answer": "dentist",
    "hint": "A doctor who fixes teeth"
  },
  {
    "id": 12,
    "imagePath": "level_178.png",
    "answer": "footballer",
    "hint": "A person playing soccer"
  },
  {
    "id": 13,
    "imagePath": "level_134.png",
    "answer": "cloudbank",
    "hint": "Large group of clouds"
  },
  {
    "id": 14,
    "imagePath": "level_16.png",
    "answer": "backpack",
    "hint": "A pack on a back"
  },
  {
    "id": 15,
    "imagePath": "level_73.png",
    "answer": "starburst",
    "hint": "A star exploding outward"
  },
  {
    "id": 16,
    "imagePath": "level_129.png",
    "answer": "fireline",
    "hint": "Line made of fire"
  },
  {
    "id": 17,
    "imagePath": "level_24.png",
    "answer": "sunglasses",
    "hint": "Suns used as glasses"
  },
  {
    "id": 18,
    "imagePath": "level_67.png",
    "answer": "toothache",
    "hint": "A tooth in pain"
  },
  {
    "id": 19,
    "imagePath": "level_54.png",
    "answer": "earring",
    "hint": "A ring on an ear"
  },
  {
    "id": 20,
    "imagePath": "level_43.png",
    "answer": "coldblooded",
    "hint": "Blood turning cold like ice"
  },
  {
    "id": 21,
    "imagePath": "level_182.png",
    "answer": "surfboard",
    "hint": "Board used for surfing waves"
  },
  {
    "id": 22,
    "imagePath": "level_96.png",
    "answer": "snowball",
    "hint": "A ball made of snow"
  },
  {
    "id": 23,
    "imagePath": "level_36.png",
    "answer": "daydream",
    "hint": "A dream floating in daytime"
  },
  {
    "id": 24,
    "imagePath": "level_142.png",
    "answer": "cloudline",
    "hint": "Line of clouds"
  },
  {
    "id": 25,
    "imagePath": "level_83.png",
    "answer": "teapot",
    "hint": "A pot pouring tea"
  },
  {
    "id": 26,
    "imagePath": "level_94.png",
    "answer": "goldfish",
    "hint": "A fish made of gold"
  },
  {
    "id": 27,
    "imagePath": "level_07.png",
    "answer": "sunflower",
    "hint": "A sun with petals"
  },
  {
    "id": 28,
    "imagePath": "level_104.png",
    "answer": "windmill",
    "hint": "A mill powered by wind"
  },
  {
    "id": 29,
    "imagePath": "level_19.png",
    "answer": "handbag",
    "hint": "A bag shaped like a hand"
  },
  {
    "id": 30,
    "imagePath": "level_138.png",
    "answer": "windpower",
    "hint": "Energy from wind"
  },
  {
    "id": 31,
    "imagePath": "level_192.png",
    "answer": "rowboat",
    "hint": "Boat moved with oars"
  },
  {
    "id": 32,
    "imagePath": "level_136.png",
    "answer": "snowcap",
    "hint": "Mountain covered in snow"
  },
  {
    "id": 33,
    "imagePath": "level_140.png",
    "answer": "moonrock",
    "hint": "A rock from the moon"
  },
  {
    "id": 34,
    "imagePath": "level_78.png",
    "answer": "toothfairy",
    "hint": "A fairy holding a tooth"
  },
  {
    "id": 35,
    "imagePath": "level_38.png",
    "answer": "sunrise",
    "hint": "The sun rising upward"
  },
  {
    "id": 36,
    "imagePath": "level_189.png",
    "answer": "submarine",
    "hint": "Vehicle traveling underwater"
  },
  {
    "id": 37,
    "imagePath": "level_11.png",
    "answer": "headphones",
    "hint": "Phones on a head"
  },
  {
    "id": 38,
    "imagePath": "level_139.png",
    "answer": "sunray",
    "hint": "A bright ray from the sun"
  },
  {
    "id": 39,
    "imagePath": "level_35.png",
    "answer": "nightfall",
    "hint": "Night is falling down"
  },
  {
    "id": 40,
    "imagePath": "level_99.png",
    "answer": "seashell",
    "hint": "A shell from the sea"
  },
  {
    "id": 41,
    "imagePath": "level_18.png",
    "answer": "haircut",
    "hint": "Hair being cut"
  },
  {
    "id": 42,
    "imagePath": "level_191.png",
    "answer": "sailboat",
    "hint": "Boat powered by sails"
  },
  {
    "id": 43,
    "imagePath": "level_64.png",
    "answer": "lightbulb",
    "hint": "A glowing bulb"
  },
  {
    "id": 44,
    "imagePath": "level_58.png",
    "answer": "snowfall",
    "hint": "Snow falling from the sky"
  },
  {
    "id": 45,
    "imagePath": "level_176.png",
    "answer": "basketball",
    "hint": "A ball used for hoops"
  },
  {
    "id": 46,
    "imagePath": "level_108.png",
    "answer": "starship",
    "hint": "A ship traveling through stars"
  },
  {
    "id": 47,
    "imagePath": "level_184.png",
    "answer": "bulldozer",
    "hint": "A heavy machine that pushes dirt"
  },
  {
    "id": 48,
    "imagePath": "level_51.png",
    "answer": "timebomb",
    "hint": "A bomb made of a clock"
  },
  {
    "id": 49,
    "imagePath": "level_87.png",
    "answer": "mailbox",
    "hint": "A box full of mail"
  },
  {
    "id": 50,
    "imagePath": "level_161.png",
    "answer": "doorway",
    "hint": "The opening where a door fits"
  },
  {
    "id": 51,
    "imagePath": "level_95.png",
    "answer": "earphone",
    "hint": "A phone in the ear"
  },
  {
    "id": 52,
    "imagePath": "level_27.png",
    "answer": "bookworm",
    "hint": "A worm reading a book"
  },
  {
    "id": 53,
    "imagePath": "level_25.png",
    "answer": "icecream",
    "hint": "Ice that screams"
  },
  {
    "id": 54,
    "imagePath": "level_131.png",
    "answer": "sunroof",
    "hint": "Roof window for sun"
  },
  {
    "id": 55,
    "imagePath": "level_133.png",
    "answer": "starpower",
    "hint": "Power from stars"
  },
  {
    "id": 56,
    "imagePath": "level_28.png",
    "answer": "facepalm",
    "hint": "A palm hitting a face"
  },
  {
    "id": 57,
    "imagePath": "level_53.png",
    "answer": "eyebrow",
    "hint": "An eye with a bow"
  },
  {
    "id": 58,
    "imagePath": "level_17.png",
    "answer": "pancake",
    "hint": "A pan and a cake"
  },
  {
    "id": 59,
    "imagePath": "level_112.png",
    "answer": "snowglobe",
    "hint": "A globe filled with snow"
  },
  {
    "id": 60,
    "imagePath": "level_03.png",
    "answer": "cupcake",
    "hint": "A cup on a cake"
  },
  {
    "id": 61,
    "imagePath": "level_200.png",
    "answer": "coffeecup",
    "hint": "Cup filled with coffee"
  },
  {
    "id": 62,
    "imagePath": "level_199.png",
    "answer": "eggplant",
    "hint": "A purple vegetable with glossy skin"
  },
  {
    "id": 63,
    "imagePath": "level_132.png",
    "answer": "moonbase",
    "hint": "Base on the moon"
  },
  {
    "id": 64,
    "imagePath": "level_39.png",
    "answer": "starfall",
    "hint": "Stars falling from the sky"
  },
  {
    "id": 65,
    "imagePath": "level_197.png",
    "answer": "toothpick",
    "hint": "A small stick used to clean teeth"
  },
  {
    "id": 66,
    "imagePath": "level_01.png",
    "answer": "forklift",
    "hint": "A fork and lifting"
  },
  {
    "id": 67,
    "imagePath": "level_130.png",
    "answer": "windchill",
    "hint": "Cold caused by wind"
  },
  {
    "id": 68,
    "imagePath": "level_15.png",
    "answer": "moonwalk",
    "hint": "The moon is walking"
  },
  {
    "id": 69,
    "imagePath": "level_147.png",
    "answer": "sundial",
    "hint": "A clock that uses the sun"
  },
  {
    "id": 70,
    "imagePath": "level_171.png",
    "answer": "downtown",
    "hint": "Center of a city"
  },
  {
    "id": 71,
    "imagePath": "level_63.png",
    "answer": "earthrise",
    "hint": "Earth rising upward"
  },
  {
    "id": 72,
    "imagePath": "level_05.png",
    "answer": "raincoat",
    "hint": "A coat made of rain"
  },
  {
    "id": 73,
    "imagePath": "level_179.png",
    "answer": "goalkeeper",
    "hint": "Player protecting the goal"
  },
  {
    "id": 74,
    "imagePath": "level_57.png",
    "answer": "rainbow",
    "hint": "Rain forming colors"
  },
  {
    "id": 75,
    "imagePath": "level_157.png",
    "answer": "teaspoon",
    "hint": "A small spoon used for tea"
  },
  {
    "id": 76,
    "imagePath": "level_146.png",
    "answer": "windgust",
    "hint": "Sudden burst of wind"
  },
  {
    "id": 77,
    "imagePath": "level_06.png",
    "answer": "toothbrush",
    "hint": "A brush and a tooth"
  },
  {
    "id": 78,
    "imagePath": "level_106.png",
    "answer": "rainboots",
    "hint": "Boots worn in rain"
  },
  {
    "id": 79,
    "imagePath": "level_90.png",
    "answer": "blueprint",
    "hint": "A blue colored plan"
  },
  {
    "id": 80,
    "imagePath": "level_194.png",
    "answer": "steamboat",
    "hint": "Boat powered by steam"
  },
  {
    "id": 81,
    "imagePath": "level_160.png",
    "answer": "doorbell",
    "hint": "A bell or button at a door"
  },
  {
    "id": 82,
    "imagePath": "level_93.png",
    "answer": "blackhole",
    "hint": "A hole colored black"
  },
  {
    "id": 83,
    "imagePath": "level_04.png",
    "answer": "milkshake",
    "hint": "Milk being shaken"
  },
  {
    "id": 84,
    "imagePath": "level_31.png",
    "answer": "moonlight",
    "hint": "Light coming from the moon"
  },
  {
    "id": 85,
    "imagePath": "level_137.png",
    "answer": "firetrail",
    "hint": "A streak of fire left behind"
  },
  {
    "id": 86,
    "imagePath": "level_13.png",
    "answer": "starfish",
    "hint": "A star shaped like a fish"
  },
  {
    "id": 87,
    "imagePath": "level_196.png",
    "answer": "shoppingcart",
    "hint": "Cart used in stores"
  },
  {
    "id": 88,
    "imagePath": "level_20.png",
    "answer": "snowboard",
    "hint": "A board made of snow"
  },
  {
    "id": 89,
    "imagePath": "level_89.png",
    "answer": "hotdog",
    "hint": "A dog on fire"
  },
  {
    "id": 90,
    "imagePath": "level_114.png",
    "answer": "windshield",
    "hint": "Glass protecting from wind"
  },
  {
    "id": 91,
    "imagePath": "level_86.png",
    "answer": "cupholder",
    "hint": "A cup holding something"
  },
  {
    "id": 92,
    "imagePath": "level_153.png",
    "answer": "dragonfly",
    "hint": "An insect with long body and wide wings"
  },
  {
    "id": 93,
    "imagePath": "level_167.png",
    "answer": "earthworm",
    "hint": "A worm that lives in soil"
  },
  {
    "id": 94,
    "imagePath": "level_145.png",
    "answer": "firelight",
    "hint": "Light from flames"
  },
  {
    "id": 95,
    "imagePath": "level_174.png",
    "answer": "insideout",
    "hint": "Turned with inside outside"
  },
  {
    "id": 96,
    "imagePath": "level_10.png",
    "answer": "sandcastle",
    "hint": "A castle made of sand"
  },
  {
    "id": 97,
    "imagePath": "level_37.png",
    "answer": "backfire",
    "hint": "Fire coming from the back"
  },
  {
    "id": 98,
    "imagePath": "level_71.png",
    "answer": "sunset",
    "hint": "The sun going down"
  },
  {
    "id": 99,
    "imagePath": "level_151.png",
    "answer": "cupboard",
    "hint": "A cabinet used to store dishes or food"
  },
  {
    "id": 100,
    "imagePath": "level_120.png",
    "answer": "snowangel",
    "hint": "Shape made in snow"
  },
  {
    "id": 101,
    "imagePath": "level_29.png",
    "answer": "handshake",
    "hint": "Hands shaking"
  },
  {
    "id": 102,
    "imagePath": "level_66.png",
    "answer": "footprint",
    "hint": "A foot leaving a mark"
  },
  {
    "id": 103,
    "imagePath": "level_34.png",
    "answer": "lipstick",
    "hint": "Lips stuck on a stick"
  },
  {
    "id": 104,
    "imagePath": "level_195.png",
    "answer": "wheelchair",
    "hint": "Chair with wheels"
  },
  {
    "id": 105,
    "imagePath": "level_60.png",
    "answer": "firestorm",
    "hint": "A storm made of fire"
  },
  {
    "id": 106,
    "imagePath": "level_47.png",
    "answer": "earthquake",
    "hint": "The earth shaking violently"
  },
  {
    "id": 107,
    "imagePath": "level_85.png",
    "answer": "snowman",
    "hint": "A man made of snow"
  },
  {
    "id": 108,
    "imagePath": "level_72.png",
    "answer": "moonfall",
    "hint": "The moon falling down"
  },
  {
    "id": 109,
    "imagePath": "level_143.png",
    "answer": "raindrop",
    "hint": "Single drop of rain"
  },
  {
    "id": 110,
    "imagePath": "level_92.png",
    "answer": "sunspot",
    "hint": "A spot on the sun"
  },
  {
    "id": 111,
    "imagePath": "level_159.png",
    "answer": "shoebox",
    "hint": "A box made to hold shoes"
  },
  {
    "id": 112,
    "imagePath": "level_26.png",
    "answer": "brainfreeze",
    "hint": "A frozen brain"
  },
  {
    "id": 113,
    "imagePath": "level_166.png",
    "answer": "snowplow",
    "hint": "Vehicle that pushes snow away"
  },
  {
    "id": 114,
    "imagePath": "level_77.png",
    "answer": "earthshake",
    "hint": "The ground shaking"
  },
  {
    "id": 115,
    "imagePath": "level_49.png",
    "answer": "lightyear",
    "hint": "A year made of light"
  },
  {
    "id": 116,
    "imagePath": "level_65.png",
    "answer": "handprint",
    "hint": "A hand leaving a mark"
  },
  {
    "id": 117,
    "imagePath": "level_59.png",
    "answer": "starshine",
    "hint": "Stars shining brightly"
  },
  {
    "id": 118,
    "imagePath": "level_198.png",
    "answer": "bathrobe",
    "hint": "A soft robe worn after washing"
  },
  {
    "id": 119,
    "imagePath": "level_76.png",
    "answer": "airflow",
    "hint": "Air moving smoothly"
  },
  {
    "id": 120,
    "imagePath": "level_105.png",
    "answer": "lighthouse",
    "hint": "A tower guiding ships with light"
  },
  {
    "id": 121,
    "imagePath": "level_101.png",
    "answer": "rainstorm",
    "hint": "Heavy rain with strong wind"
  },
  {
    "id": 122,
    "imagePath": "level_175.png",
    "answer": "football",
    "hint": "A ball used in soccer"
  },
  {
    "id": 123,
    "imagePath": "level_23.png",
    "answer": "firefly",
    "hint": "A flying flame"
  },
  {
    "id": 124,
    "imagePath": "level_69.png",
    "answer": "headstart",
    "hint": "A head starting first"
  },
  {
    "id": 125,
    "imagePath": "level_181.png",
    "answer": "skateboard",
    "hint": "Board with wheels for riding"
  },
  {
    "id": 126,
    "imagePath": "level_02.png",
    "answer": "butterfly",
    "hint": "Butter with wings"
  },
  {
    "id": 127,
    "imagePath": "level_150.png",
    "answer": "cloudscape",
    "hint": "View filled with clouds"
  },
  {
    "id": 128,
    "imagePath": "level_91.png",
    "answer": "notebook",
    "hint": "A book saying no"
  },
  {
    "id": 129,
    "imagePath": "level_12.png",
    "answer": "toothpaste",
    "hint": "A tooth inside pasta"
  },
  {
    "id": 130,
    "imagePath": "level_169.png",
    "answer": "whiteboard",
    "hint": "Board used with markers"
  },
  {
    "id": 131,
    "imagePath": "level_32.png",
    "answer": "candy",
    "hint": "Something sweet all people like to eat"
  },
  {
    "id": 132,
    "imagePath": "level_125.png",
    "answer": "starfield",
    "hint": "Sky full of stars"
  },
  {
    "id": 133,
    "imagePath": "level_177.png",
    "answer": "baseball",
    "hint": "A small white sports ball"
  },
  {
    "id": 134,
    "imagePath": "level_148.png",
    "answer": "moonrise",
    "hint": "Moon coming up"
  },
  {
    "id": 135,
    "imagePath": "level_100.png",
    "answer": "shoelace",
    "hint": "Lace on a shoe"
  },
  {
    "id": 136,
    "imagePath": "level_126.png",
    "answer": "cloudcover",
    "hint": "Sky covered with clouds"
  },
  {
    "id": 137,
    "imagePath": "level_122.png",
    "answer": "windstorm",
    "hint": "A storm with strong wind"
  },
  {
    "id": 138,
    "imagePath": "level_70.png",
    "answer": "heartburn",
    "hint": "A burning heart"
  },
  {
    "id": 139,
    "imagePath": "level_45.png",
    "answer": "firework",
    "hint": "Someone working inside fire"
  },
  {
    "id": 140,
    "imagePath": "level_109.png",
    "answer": "cloudburst",
    "hint": "Cloud releasing heavy rain"
  },
  {
    "id": 141,
    "imagePath": "level_80.png",
    "answer": "butterknife",
    "hint": "A knife made of butter"
  },
  {
    "id": 142,
    "imagePath": "level_173.png",
    "answer": "underground",
    "hint": "Below the surface"
  },
  {
    "id": 143,
    "imagePath": "level_170.png",
    "answer": "backyard",
    "hint": "Area behind a house"
  },
  {
    "id": 144,
    "imagePath": "level_193.png",
    "answer": "lifeboat",
    "hint": "Boat used for rescue"
  },
  {
    "id": 145,
    "imagePath": "level_79.png",
    "answer": "catfish",
    "hint": "A fish with a cat face"
  },
  {
    "id": 146,
    "imagePath": "level_144.png",
    "answer": "snowdrift",
    "hint": "Snow piled by the wind"
  },
  {
    "id": 147,
    "imagePath": "level_156.png",
    "answer": "starfruit",
    "hint": "A fruit shaped like a star"
  },
  {
    "id": 148,
    "imagePath": "level_188.png",
    "answer": "spaceship",
    "hint": "Vehicle traveling in space"
  },
  {
    "id": 149,
    "imagePath": "level_113.png",
    "answer": "fireplace",
    "hint": "A place for burning fire"
  },
  {
    "id": 150,
    "imagePath": "level_127.png",
    "answer": "rainfall",
    "hint": "Rain coming down"
  },
  {
    "id": 151,
    "imagePath": "level_190.png",
    "answer": "speedboat",
    "hint": "A fast boat"
  },
  {
    "id": 152,
    "imagePath": "level_121.png",
    "answer": "fireproof",
    "hint": "Protected from fire"
  },
  {
    "id": 153,
    "imagePath": "level_61.png",
    "answer": "airdrop",
    "hint": "Something dropping from air"
  },
  {
    "id": 154,
    "imagePath": "level_41.png",
    "answer": "headache",
    "hint": "A head in visible pain"
  },
  {
    "id": 155,
    "imagePath": "level_09.png",
    "answer": "fireman",
    "hint": "A man made of fire"
  },
  {
    "id": 156,
    "imagePath": "level_88.png",
    "answer": "popcorn",
    "hint": "Corn popping"
  },
  {
    "id": 157,
    "imagePath": "level_40.png",
    "answer": "fingerprint",
    "hint": "A finger printing on paper"
  },
  {
    "id": 158,
    "imagePath": "level_33.png",
    "answer": "brainwash",
    "hint": "A brain being washed"
  },
  {
    "id": 159,
    "imagePath": "level_46.png",
    "answer": "mindblown",
    "hint": "A mind exploding outward"
  },
  {
    "id": 160,
    "imagePath": "level_115.png",
    "answer": "sunshade",
    "hint": "Shade blocking the sun"
  },
  {
    "id": 161,
    "imagePath": "level_124.png",
    "answer": "moonphase",
    "hint": "Different shapes of moon"
  },
  {
    "id": 162,
    "imagePath": "level_187.png",
    "answer": "helicopter",
    "hint": "Aircraft with spinning blades"
  },
  {
    "id": 163,
    "imagePath": "level_97.png",
    "answer": "fireball",
    "hint": "A ball made of fire"
  },
  {
    "id": 164,
    "imagePath": "level_52.png",
    "answer": "deadline",
    "hint": "A literal dead line"
  },
  {
    "id": 165,
    "imagePath": "level_08.png",
    "answer": "bookcase",
    "hint": "A book in a case"
  },
  {
    "id": 166,
    "imagePath": "level_186.png",
    "answer": "ambulance",
    "hint": "Emergency medical vehicle"
  },
  {
    "id": 167,
    "imagePath": "level_21.png",
    "answer": "timeflies",
    "hint": "A clock flying"
  },
  {
    "id": 168,
    "imagePath": "level_110.png",
    "answer": "sandstorm",
    "hint": "A storm made of sand"
  },
  {
    "id": 169,
    "imagePath": "level_119.png",
    "answer": "raincheck",
    "hint": "Checking in the rain"
  },
  {
    "id": 170,
    "imagePath": "level_14.png",
    "answer": "keyboard",
    "hint": "Keys on a board"
  },
  {
    "id": 171,
    "imagePath": "level_185.png",
    "answer": "policecar",
    "hint": "Car used by police"
  },
  {
    "id": 172,
    "imagePath": "level_117.png",
    "answer": "startrail",
    "hint": "Stars leaving a trail"
  },
  {
    "id": 173,
    "imagePath": "level_103.png",
    "answer": "firetruck",
    "hint": "A truck for fighting fire"
  },
  {
    "id": 174,
    "imagePath": "level_154.png",
    "answer": "jellyfish",
    "hint": "A soft sea creature with tentacles"
  },
  {
    "id": 175,
    "imagePath": "level_163.png",
    "answer": "mailman",
    "hint": "A person delivering letters"
  },
  {
    "id": 176,
    "imagePath": "level_55.png",
    "answer": "moonstone",
    "hint": "A stone from the moon"
  },
  {
    "id": 177,
    "imagePath": "level_68.png",
    "answer": "eyedrop",
    "hint": "A drop from the eye"
  },
  {
    "id": 178,
    "imagePath": "level_56.png",
    "answer": "sunbeam",
    "hint": "A beam of sunlight"
  },
  {
    "id": 179,
    "imagePath": "level_128.png",
    "answer": "snowstorm",
    "hint": "Storm with heavy snow"
  },
  {
    "id": 180,
    "imagePath": "level_165.png",
    "answer": "newborn",
    "hint": "A baby just born"
  },
  {
    "id": 181,
    "imagePath": "level_82.png",
    "answer": "fishbowl",
    "hint": "A bowl shaped like a fish"
  },
  {
    "id": 182,
    "imagePath": "level_62.png",
    "answer": "waterflow",
    "hint": "Water flowing continuously"
  },
  {
    "id": 183,
    "imagePath": "level_111.png",
    "answer": "teacup",
    "hint": "A small cup for tea"
  },
  {
    "id": 184,
    "imagePath": "level_102.png",
    "answer": "snowflake",
    "hint": "A single piece of falling snow"
  },
  {
    "id": 185,
    "imagePath": "level_44.png",
    "answer": "silverfish",
    "hint": "A fish made of silver"
  },
  {
    "id": 186,
    "imagePath": "level_50.png",
    "answer": "waterfall",
    "hint": "Water literally falling"
  },
  {
    "id": 187,
    "imagePath": "level_155.png",
    "answer": "ladybug",
    "hint": "A small red insect with black spots"
  },
  {
    "id": 188,
    "imagePath": "level_81.png",
    "answer": "bookend",
    "hint": "A book at the end"
  },
  {
    "id": 189,
    "imagePath": "level_180.png",
    "answer": "snowboarder",
    "hint": "Person riding a snowboard"
  },
  {
    "id": 190,
    "imagePath": "level_116.png",
    "answer": "moonbeam",
    "hint": "Light from the moon"
  },
  {
    "id": 191,
    "imagePath": "level_30.png",
    "answer": "heartbreak",
    "hint": "A broken heart"
  },
  {
    "id": 192,
    "imagePath": "level_135.png",
    "answer": "raincloud",
    "hint": "Cloud bringing rain"
  },
  {
    "id": 193,
    "imagePath": "level_162.png",
    "answer": "bookshelf",
    "hint": "A shelf used to hold books"
  },
  {
    "id": 194,
    "imagePath": "level_168.png",
    "answer": "blackboard",
    "hint": "Board used with chalk"
  },
  {
    "id": 195,
    "imagePath": "level_149.png",
    "answer": "starlight",
    "hint": "Light from stars"
  },
  {
    "id": 196,
    "imagePath": "level_74.png",
    "answer": "firecracker",
    "hint": "A cracking fire explosion"
  },
  {
    "id": 197,
    "imagePath": "level_98.png",
    "answer": "handmade",
    "hint": "Made by a hand"
  },
  {
    "id": 198,
    "imagePath": "level_141.png",
    "answer": "starpath",
    "hint": "A glowing path of stars"
  },
  {
    "id": 199,
    "imagePath": "level_84.png",
    "answer": "bedrock",
    "hint": "A rock shaped like a bed"
  },
  {
    "id": 200,
    "imagePath": "level_164.png",
    "answer": "newspaper",
    "hint": "Printed pages with daily news"
  }
]
